setup.py
hgpaste/__init__.py
hgpaste/factory.py
hgpaste.egg-info/PKG-INFO
hgpaste.egg-info/SOURCES.txt
hgpaste.egg-info/dependency_links.txt
hgpaste.egg-info/entry_points.txt
hgpaste.egg-info/not-zip-safe
hgpaste.egg-info/requires.txt
hgpaste.egg-info/top_level.txt