Metadata-Version: 1.0
Name: hgpaste
Version: 0.1.1
Summary: front-end to serve a hg webdir with paste and other
Home-page: http://k0s.org
Author: Jeff Hammel
Author-email: k0scist@gmail.com
License: GPL
Keywords: paste hg
Platform: UNKNOWN
